{
  "House Tigra": {
    "url": "https://www.booking.com/hotel/hr/apartment-tigra.de.html?label=gen173nr-1FCAEoggI46AdIB1gEaDuIAQGYAQe4AQfIAQzYAQHoAQH4AQKIAgGoAgO4ArLCnaAGwAIB0gIkZjk0MzE1NzYtNjJiYS00OTcyLTgwMWEtOGU1NTgyOGQ1OWE52AIF4AIB&aid=304142&ucfs=1&arphpl=1&checkin=2023-06-03&checkout=2023-06-12&dest_id=-94604&dest_type=city&group_adults=2&req_adults=2&no_rooms=1&group_children=0&req_children=0&hpos=1&hapos=1&sr_order=popularity&nflt=distance%3D1000%3Boos%3D1%3Breview_score%3D80&srpvid=48956c0ec3e60246&srepoch=1678288927&all_sr_blocks=181194601_344145885_0_0_0&highlighted_blocks=181194601_344145885_0_0_0&matching_block_id=181194601_344145885_0_0_0&sr_pri_blocks=181194601_344145885_0_0_0__126100&from=searchresults#hotelTmpl",
    "title": "House Tigra",
    "price": "US$1.335"
  },
  "Studio Apartment ORATORIO": {
    "url": "https://www.booking.com/hotel/hr/studio-apartment-oratorio.de.html?label=gen173nr-1FCAEoggI46AdIB1gEaDuIAQGYAQe4AQfIAQzYAQHoAQH4AQKIAgGoAgO4ArLCnaAGwAIB0gIkZjk0MzE1NzYtNjJiYS00OTcyLTgwMWEtOGU1NTgyOGQ1OWE52AIF4AIB&aid=304142&ucfs=1&arphpl=1&checkin=2023-06-03&checkout=2023-06-12&dest_id=-94604&dest_type=city&group_adults=2&req_adults=2&no_rooms=1&group_children=0&req_children=0&hpos=2&hapos=2&sr_order=popularity&nflt=distance%3D1000%3Boos%3D1%3Breview_score%3D80&srpvid=48956c0ec3e60246&srepoch=1678288927&all_sr_blocks=659532201_327698796_2_0_0&highlighted_blocks=659532201_327698796_2_0_0&matching_block_id=659532201_327698796_2_0_0&sr_pri_blocks=659532201_327698796_2_0_0__144000&from=searchresults#hotelTmpl",
    "title": "Studio Apartment ORATORIO",
    "price": "US$1.524"
  },
  "Maistra Select Island Hotel Katarina": {
    "url": "https://www.booking.com/hotel/hr/katarina.de.html?label=gen173nr-1FCAEoggI46AdIB1gEaDuIAQGYAQe4AQfIAQzYAQHoAQH4AQKIAgGoAgO4ArLCnaAGwAIB0gIkZjk0MzE1NzYtNjJiYS00OTcyLTgwMWEtOGU1NTgyOGQ1OWE52AIF4AIB&aid=304142&ucfs=1&arphpl=1&checkin=2023-06-03&checkout=2023-06-12&dest_id=-94604&dest_type=city&group_adults=2&req_adults=2&no_rooms=1&group_children=0&req_children=0&hpos=3&hapos=3&sr_order=popularity&nflt=distance%3D1000%3Boos%3D1%3Breview_score%3D80&srpvid=48956c0ec3e60246&srepoch=1678288927&all_sr_blocks=2137701_106031484_0_33_0&highlighted_blocks=2137701_106031484_0_33_0&matching_block_id=2137701_106031484_0_33_0&sr_pri_blocks=2137701_106031484_0_33_0__218070&from=searchresults#hotelTmpl",
    "title": "Maistra Select Island Hotel Katarina",
    "price": "US$2.308"
  },
  "Central Apartments Circolo": {
    "url": "https://www.booking.com/hotel/hr/central-apartments-circolo-rovinj.de.html?label=gen173nr-1FCAEoggI46AdIB1gEaDuIAQGYAQe4AQfIAQzYAQHoAQH4AQKIAgGoAgO4ArLCnaAGwAIB0gIkZjk0MzE1NzYtNjJiYS00OTcyLTgwMWEtOGU1NTgyOGQ1OWE52AIF4AIB&aid=304142&ucfs=1&arphpl=1&checkin=2023-06-03&checkout=2023-06-12&dest_id=-94604&dest_type=city&group_adults=2&req_adults=2&no_rooms=1&group_children=0&req_children=0&hpos=4&hapos=4&sr_order=popularity&nflt=distance%3D1000%3Boos%3D1%3Breview_score%3D80&srpvid=48956c0ec3e60246&srepoch=1678288927&all_sr_blocks=186550801_120534066_2_0_0&highlighted_blocks=186550801_120534066_2_0_0&matching_block_id=186550801_120534066_2_0_0&sr_pri_blocks=186550801_120534066_2_0_0__178200&from=searchresults#hotelTmpl",
    "title": "Central Apartments Circolo",
    "price": "US$1.886"
  },
  "Apartments & Rooms La casa Barbaro": {
    "url": "https://www.booking.com/hotel/hr/apartments-amp-rooms-quot-casa-tipica-quot.de.html?label=gen173nr-1FCAEoggI46AdIB1gEaDuIAQGYAQe4AQfIAQzYAQHoAQH4AQKIAgGoAgO4ArLCnaAGwAIB0gIkZjk0MzE1NzYtNjJiYS00OTcyLTgwMWEtOGU1NTgyOGQ1OWE52AIF4AIB&aid=304142&ucfs=1&arphpl=1&checkin=2023-06-03&checkout=2023-06-12&dest_id=-94604&dest_type=city&group_adults=2&req_adults=2&no_rooms=1&group_children=0&req_children=0&hpos=5&hapos=5&sr_order=popularity&nflt=distance%3D1000%3Boos%3D1%3Breview_score%3D80&srpvid=48956c0ec3e60246&srepoch=1678288927&all_sr_blocks=183228803_344639454_0_0_0&highlighted_blocks=183228803_344639454_0_0_0&matching_block_id=183228803_344639454_0_0_0&sr_pri_blocks=183228803_344639454_0_0_0__191250&from_sustainable_property_sr=1&from=searchresults#hotelTmpl",
    "title": "Apartments & Rooms La casa Barbaro",
    "price": "US$2.024"
  },
  "Grand Park Hotel Rovinj by Maistra Collection": {
    "url": "https://www.booking.com/hotel/hr/grand-park-rovinj.de.html?label=gen173nr-1FCAEoggI46AdIB1gEaDuIAQGYAQe4AQfIAQzYAQHoAQH4AQKIAgGoAgO4ArLCnaAGwAIB0gIkZjk0MzE1NzYtNjJiYS00OTcyLTgwMWEtOGU1NTgyOGQ1OWE52AIF4AIB&aid=304142&ucfs=1&arphpl=1&checkin=2023-06-03&checkout=2023-06-12&dest_id=-94604&dest_type=city&group_adults=2&req_adults=2&no_rooms=1&group_children=0&req_children=0&hpos=6&hapos=6&sr_order=popularity&nflt=distance%3D1000%3Boos%3D1%3Breview_score%3D80&srpvid=48956c0ec3e60246&srepoch=1678288927&all_sr_blocks=410935201_215714693_0_1_0&highlighted_blocks=410935201_215714693_0_1_0&matching_block_id=410935201_215714693_0_1_0&sr_pri_blocks=410935201_215714693_0_1_0__605700&from_sustainable_property_sr=1&from=searchresults#hotelTmpl",
    "title": "Grand Park Hotel Rovinj by Maistra Collection",
    "price": "US$6.412"
  },
  "Sunset Residence Rovinj": {
    "url": "https://www.booking.com/hotel/hr/villa-tomo-rovinj.de.html?label=gen173nr-1FCAEoggI46AdIB1gEaDuIAQGYAQe4AQfIAQzYAQHoAQH4AQKIAgGoAgO4ArLCnaAGwAIB0gIkZjk0MzE1NzYtNjJiYS00OTcyLTgwMWEtOGU1NTgyOGQ1OWE52AIF4AIB&aid=304142&ucfs=1&arphpl=1&checkin=2023-06-03&checkout=2023-06-12&dest_id=-94604&dest_type=city&group_adults=2&req_adults=2&no_rooms=1&group_children=0&req_children=0&hpos=7&hapos=7&sr_order=popularity&nflt=distance%3D1000%3Boos%3D1%3Breview_score%3D80&srpvid=48956c0ec3e60246&srepoch=1678288927&all_sr_blocks=479515716_363195092_0_0_0&highlighted_blocks=479515716_363195092_0_0_0&matching_block_id=479515716_363195092_0_0_0&sr_pri_blocks=479515716_363195092_0_0_0__187000&from=searchresults#hotelTmpl",
    "title": "Sunset Residence Rovinj",
    "price": "US$1.979"
  },
  "Rooms & Apartments La Casa di Loreto": {
    "url": "https://www.booking.com/hotel/hr/la-casa-di-loreto.de.html?label=gen173nr-1FCAEoggI46AdIB1gEaDuIAQGYAQe4AQfIAQzYAQHoAQH4AQKIAgGoAgO4ArLCnaAGwAIB0gIkZjk0MzE1NzYtNjJiYS00OTcyLTgwMWEtOGU1NTgyOGQ1OWE52AIF4AIB&aid=304142&ucfs=1&arphpl=1&checkin=2023-06-03&checkout=2023-06-12&dest_id=-94604&dest_type=city&group_adults=2&req_adults=2&no_rooms=1&group_children=0&req_children=0&hpos=8&hapos=8&sr_order=popularity&nflt=distance%3D1000%3Boos%3D1%3Breview_score%3D80&srpvid=48956c0ec3e60246&srepoch=1678288927&all_sr_blocks=59401905_326535435_0_0_0&highlighted_blocks=59401905_326535435_0_0_0&matching_block_id=59401905_326535435_0_0_0&sr_pri_blocks=59401905_326535435_0_0_0__154100&from=searchresults#hotelTmpl",
    "title": "Rooms & Apartments La Casa di Loreto",
    "price": "US$1.631"
  },
  "Bianco Rosa": {
    "url": "https://www.booking.com/hotel/hr/bianco-rosa.de.html?label=gen173nr-1FCAEoggI46AdIB1gEaDuIAQGYAQe4AQfIAQzYAQHoAQH4AQKIAgGoAgO4ArLCnaAGwAIB0gIkZjk0MzE1NzYtNjJiYS00OTcyLTgwMWEtOGU1NTgyOGQ1OWE52AIF4AIB&aid=304142&ucfs=1&arphpl=1&checkin=2023-06-03&checkout=2023-06-12&dest_id=-94604&dest_type=city&group_adults=2&req_adults=2&no_rooms=1&group_children=0&req_children=0&hpos=9&hapos=9&sr_order=popularity&nflt=distance%3D1000%3Boos%3D1%3Breview_score%3D80&srpvid=48956c0ec3e60246&srepoch=1678288927&all_sr_blocks=851849204_369030822_0_0_0&highlighted_blocks=851849204_369030822_0_0_0&matching_block_id=851849204_369030822_0_0_0&sr_pri_blocks=851849204_369030822_0_0_0__194400&from=searchresults#hotelTmpl",
    "title": "Bianco Rosa",
    "price": "US$2.058"
  },
  "Noemi's rooms": {
    "url": "https://www.booking.com/hotel/hr/noemi-39-s-rooms.de.html?label=gen173nr-1FCAEoggI46AdIB1gEaDuIAQGYAQe4AQfIAQzYAQHoAQH4AQKIAgGoAgO4ArLCnaAGwAIB0gIkZjk0MzE1NzYtNjJiYS00OTcyLTgwMWEtOGU1NTgyOGQ1OWE52AIF4AIB&aid=304142&ucfs=1&arphpl=1&checkin=2023-06-03&checkout=2023-06-12&dest_id=-94604&dest_type=city&group_adults=2&req_adults=2&no_rooms=1&group_children=0&req_children=0&hpos=10&hapos=10&sr_order=popularity&nflt=distance%3D1000%3Boos%3D1%3Breview_score%3D80&srpvid=48956c0ec3e60246&srepoch=1678288927&all_sr_blocks=350460001_285280250_0_0_0&highlighted_blocks=350460001_285280250_0_0_0&matching_block_id=350460001_285280250_0_0_0&sr_pri_blocks=350460001_285280250_0_0_0__172500&from=searchresults#hotelTmpl",
    "title": "Noemi's rooms",
    "price": "US$1.826"
  },
  "Blubini Heritage House": {
    "url": "https://www.booking.com/hotel/hr/blubini-heritage.de.html?label=gen173nr-1FCAEoggI46AdIB1gEaDuIAQGYAQe4AQfIAQzYAQHoAQH4AQKIAgGoAgO4ArLCnaAGwAIB0gIkZjk0MzE1NzYtNjJiYS00OTcyLTgwMWEtOGU1NTgyOGQ1OWE52AIF4AIB&aid=304142&ucfs=1&arphpl=1&checkin=2023-06-03&checkout=2023-06-12&dest_id=-94604&dest_type=city&group_adults=2&req_adults=2&no_rooms=1&group_children=0&req_children=0&hpos=11&hapos=11&sr_order=popularity&nflt=distance%3D1000%3Boos%3D1%3Breview_score%3D80&srpvid=48956c0ec3e60246&srepoch=1678288927&all_sr_blocks=529225401_298938755_0_1_0&highlighted_blocks=529225401_298938755_0_1_0&matching_block_id=529225401_298938755_0_1_0&sr_pri_blocks=529225401_298938755_0_1_0__250173&from_sustainable_property_sr=1&from=searchresults#hotelTmpl",
    "title": "Blubini Heritage House",
    "price": "US$2.648"
  },
  "Hotel Arupinum": {
    "url": "https://www.booking.com/hotel/hr/arupinium.de.html?label=gen173nr-1FCAEoggI46AdIB1gEaDuIAQGYAQe4AQfIAQzYAQHoAQH4AQKIAgGoAgO4ArLCnaAGwAIB0gIkZjk0MzE1NzYtNjJiYS00OTcyLTgwMWEtOGU1NTgyOGQ1OWE52AIF4AIB&aid=304142&ucfs=1&arphpl=1&checkin=2023-06-03&checkout=2023-06-12&dest_id=-94604&dest_type=city&group_adults=2&req_adults=2&no_rooms=1&group_children=0&req_children=0&hpos=12&hapos=12&sr_order=popularity&nflt=distance%3D1000%3Boos%3D1%3Breview_score%3D80&srpvid=48956c0ec3e60246&srepoch=1678288927&all_sr_blocks=46797502_89090472_0_1_0&highlighted_blocks=46797502_89090472_0_1_0&matching_block_id=46797502_89090472_0_1_0&sr_pri_blocks=46797502_89090472_0_1_0__265680&from=searchresults#hotelTmpl",
    "title": "Hotel Arupinum",
    "price": "US$2.812"
  },
  "ANTICA PORTA sul Mar - by Porta Antica": {
    "url": "https://www.booking.com/hotel/hr/antica-porta-sul-mar.de.html?label=gen173nr-1FCAEoggI46AdIB1gEaDuIAQGYAQe4AQfIAQzYAQHoAQH4AQKIAgGoAgO4ArLCnaAGwAIB0gIkZjk0MzE1NzYtNjJiYS00OTcyLTgwMWEtOGU1NTgyOGQ1OWE52AIF4AIB&aid=304142&ucfs=1&arphpl=1&checkin=2023-06-03&checkout=2023-06-12&dest_id=-94604&dest_type=city&group_adults=2&req_adults=2&no_rooms=1&group_children=0&req_children=0&hpos=13&hapos=13&sr_order=popularity&nflt=distance%3D1000%3Boos%3D1%3Breview_score%3D80&srpvid=48956c0ec3e60246&srepoch=1678288927&all_sr_blocks=209636703_369597017_0_0_0&highlighted_blocks=209636703_369597017_0_0_0&matching_block_id=209636703_369597017_0_0_0&sr_pri_blocks=209636703_369597017_0_0_0__160500&from_sustainable_property_sr=1&from=searchresults#hotelTmpl",
    "title": "ANTICA PORTA sul Mar - by Porta Antica",
    "price": "US$1.699"
  },
  "B&B Palace Basilico 1580.": {
    "url": "https://www.booking.com/hotel/hr/b-amp-b-palace-basilico-1580.de.html?label=gen173nr-1FCAEoggI46AdIB1gEaDuIAQGYAQe4AQfIAQzYAQHoAQH4AQKIAgGoAgO4ArLCnaAGwAIB0gIkZjk0MzE1NzYtNjJiYS00OTcyLTgwMWEtOGU1NTgyOGQ1OWE52AIF4AIB&aid=304142&ucfs=1&arphpl=1&checkin=2023-06-03&checkout=2023-06-12&dest_id=-94604&dest_type=city&group_adults=2&req_adults=2&no_rooms=1&group_children=0&req_children=0&hpos=14&hapos=14&sr_order=popularity&nflt=distance%3D1000%3Boos%3D1%3Breview_score%3D80&srpvid=48956c0ec3e60246&srepoch=1678288927&all_sr_blocks=855173001_353034211_0_2_0&highlighted_blocks=855173001_353034211_0_2_0&matching_block_id=855173001_353034211_0_2_0&sr_pri_blocks=855173001_353034211_0_2_0__151875&from=searchresults#hotelTmpl",
    "title": "B&B Palace Basilico 1580.",
    "price": "US$1.608"
  },
  "Hotel Angelo d'Oro": {
    "url": "https://www.booking.com/hotel/hr/villa-angelo-d-oro.de.html?label=gen173nr-1FCAEoggI46AdIB1gEaDuIAQGYAQe4AQfIAQzYAQHoAQH4AQKIAgGoAgO4ArLCnaAGwAIB0gIkZjk0MzE1NzYtNjJiYS00OTcyLTgwMWEtOGU1NTgyOGQ1OWE52AIF4AIB&aid=304142&ucfs=1&arphpl=1&checkin=2023-06-03&checkout=2023-06-12&dest_id=-94604&dest_type=city&group_adults=2&req_adults=2&no_rooms=1&group_children=0&req_children=0&hpos=15&hapos=15&sr_order=popularity&nflt=distance%3D1000%3Boos%3D1%3Breview_score%3D80&srpvid=48956c0ec3e60246&srepoch=1678288927&all_sr_blocks=2111215_95145646_0_1_0&highlighted_blocks=2111215_95145646_0_1_0&matching_block_id=2111215_95145646_0_1_0&sr_pri_blocks=2111215_95145646_0_1_0__202077&from=searchresults#hotelTmpl",
    "title": "Hotel Angelo d'Oro",
    "price": "US$2.139"
  },
  "Boutique Residence Arion": {
    "url": "https://www.booking.com/hotel/hr/boutique-residence-arion.de.html?label=gen173nr-1FCAEoggI46AdIB1gEaDuIAQGYAQe4AQfIAQzYAQHoAQH4AQKIAgGoAgO4ArLCnaAGwAIB0gIkZjk0MzE1NzYtNjJiYS00OTcyLTgwMWEtOGU1NTgyOGQ1OWE52AIF4AIB&aid=304142&ucfs=1&arphpl=1&checkin=2023-06-03&checkout=2023-06-12&dest_id=-94604&dest_type=city&group_adults=2&req_adults=2&no_rooms=1&group_children=0&req_children=0&hpos=16&hapos=16&sr_order=popularity&nflt=distance%3D1000%3Boos%3D1%3Breview_score%3D80&srpvid=48956c0ec3e60246&srepoch=1678288927&all_sr_blocks=845076202_353023515_2_1_0&highlighted_blocks=845076202_353023515_2_1_0&matching_block_id=845076202_353023515_2_1_0&sr_pri_blocks=845076202_353023515_2_1_0__214700&from_sustainable_property_sr=1&from=searchresults#hotelTmpl",
    "title": "Boutique Residence Arion",
    "price": "US$2.273"
  },
  "Contrada del Nonno Apartments (city center - private parking on-site)": {
    "url": "https://www.booking.com/hotel/hr/apartments-martina-with-private-parking.de.html?label=gen173nr-1FCAEoggI46AdIB1gEaDuIAQGYAQe4AQfIAQzYAQHoAQH4AQKIAgGoAgO4ArLCnaAGwAIB0gIkZjk0MzE1NzYtNjJiYS00OTcyLTgwMWEtOGU1NTgyOGQ1OWE52AIF4AIB&aid=304142&ucfs=1&arphpl=1&checkin=2023-06-03&checkout=2023-06-12&dest_id=-94604&dest_type=city&group_adults=2&req_adults=2&no_rooms=1&group_children=0&req_children=0&hpos=17&hapos=17&sr_order=popularity&nflt=distance%3D1000%3Boos%3D1%3Breview_score%3D80&srpvid=48956c0ec3e60246&srepoch=1678288927&all_sr_blocks=142926008_336007931_2_0_0&highlighted_blocks=142926008_336007931_2_0_0&matching_block_id=142926008_336007931_2_0_0&sr_pri_blocks=142926008_336007931_2_0_0__216000&from_sustainable_property_sr=1&from=searchresults#hotelTmpl",
    "title": "Contrada del Nonno Apartments (city center - private parking on-site)",
    "price": "US$2.286"
  },
  "Apartment in the Heart of Carera Street": {
    "url": "https://www.booking.com/hotel/hr/rovinj-apartment-carera-34.de.html?label=gen173nr-1FCAEoggI46AdIB1gEaDuIAQGYAQe4AQfIAQzYAQHoAQH4AQKIAgGoAgO4ArLCnaAGwAIB0gIkZjk0MzE1NzYtNjJiYS00OTcyLTgwMWEtOGU1NTgyOGQ1OWE52AIF4AIB&aid=304142&ucfs=1&arphpl=1&checkin=2023-06-03&checkout=2023-06-12&dest_id=-94604&dest_type=city&group_adults=2&req_adults=2&no_rooms=1&group_children=0&req_children=0&hpos=18&hapos=18&sr_order=popularity&nflt=distance%3D1000%3Boos%3D1%3Breview_score%3D80&srpvid=48956c0ec3e60246&srepoch=1678288927&all_sr_blocks=718494801_304107606_2_0_0&highlighted_blocks=718494801_304107606_2_0_0&matching_block_id=718494801_304107606_2_0_0&sr_pri_blocks=718494801_304107606_2_0_0__135600&from=searchresults#hotelTmpl",
    "title": "Apartment in the Heart of Carera Street",
    "price": "US$1.435"
  },
  "Leone Sea view Apartment": {
    "url": "https://www.booking.com/hotel/hr/leone-sea-view-apartment.de.html?label=gen173nr-1FCAEoggI46AdIB1gEaDuIAQGYAQe4AQfIAQzYAQHoAQH4AQKIAgGoAgO4ArLCnaAGwAIB0gIkZjk0MzE1NzYtNjJiYS00OTcyLTgwMWEtOGU1NTgyOGQ1OWE52AIF4AIB&aid=304142&ucfs=1&arphpl=1&checkin=2023-06-03&checkout=2023-06-12&dest_id=-94604&dest_type=city&group_adults=2&req_adults=2&no_rooms=1&group_children=0&req_children=0&hpos=19&hapos=19&sr_order=popularity&nflt=distance%3D1000%3Boos%3D1%3Breview_score%3D80&srpvid=48956c0ec3e60246&srepoch=1678288927&all_sr_blocks=886682602_358403494_2_0_0&highlighted_blocks=886682602_358403494_2_0_0&matching_block_id=886682602_358403494_2_0_0&sr_pri_blocks=886682602_358403494_2_0_0__163800&from=searchresults#hotelTmpl",
    "title": "Leone Sea view Apartment",
    "price": "US$1.734"
  },
  "Central New Apartment Nonna Mara": {
    "url": "https://www.booking.com/hotel/hr/central-new-apartment-nonna-mara.de.html?label=gen173nr-1FCAEoggI46AdIB1gEaDuIAQGYAQe4AQfIAQzYAQHoAQH4AQKIAgGoAgO4ArLCnaAGwAIB0gIkZjk0MzE1NzYtNjJiYS00OTcyLTgwMWEtOGU1NTgyOGQ1OWE52AIF4AIB&aid=304142&ucfs=1&arphpl=1&checkin=2023-06-03&checkout=2023-06-12&dest_id=-94604&dest_type=city&group_adults=2&req_adults=2&no_rooms=1&group_children=0&req_children=0&hpos=20&hapos=20&sr_order=popularity&nflt=distance%3D1000%3Boos%3D1%3Breview_score%3D80&srpvid=48956c0ec3e60246&srepoch=1678288927&all_sr_blocks=327784001_348466890_0_0_0&highlighted_blocks=327784001_348466890_0_0_0&matching_block_id=327784001_348466890_0_0_0&sr_pri_blocks=327784001_348466890_0_0_0__164000&from=searchresults#hotelTmpl",
    "title": "Central New Apartment Nonna Mara",
    "price": "US$1.736"
  },
  "Danijela Rovinj sea view and free parking": {
    "url": "https://www.booking.com/hotel/hr/studio-arsen.de.html?label=gen173nr-1FCAEoggI46AdIB1gEaDuIAQGYAQe4AQfIAQzYAQHoAQH4AQKIAgGoAgO4ArLCnaAGwAIB0gIkZjk0MzE1NzYtNjJiYS00OTcyLTgwMWEtOGU1NTgyOGQ1OWE52AIF4AIB&aid=304142&ucfs=1&arphpl=1&checkin=2023-06-03&checkout=2023-06-12&dest_id=-94604&dest_type=city&group_adults=2&req_adults=2&no_rooms=1&group_children=0&req_children=0&hpos=21&hapos=21&sr_order=popularity&nflt=distance%3D1000%3Boos%3D1%3Breview_score%3D80&srpvid=48956c0ec3e60246&srepoch=1678288927&all_sr_blocks=326099703_329601812_2_0_0&highlighted_blocks=326099703_329601812_2_0_0&matching_block_id=326099703_329601812_2_0_0&sr_pri_blocks=326099703_329601812_2_0_0__130500&from_sustainable_property_sr=1&from=searchresults#hotelTmpl",
    "title": "Danijela Rovinj sea view and free parking",
    "price": "US$1.381"
  },
  "Happy House Bregovita by Irundo": {
    "url": "https://www.booking.com/hotel/hr/happy-house-bregovita.de.html?label=gen173nr-1FCAEoggI46AdIB1gEaDuIAQGYAQe4AQfIAQzYAQHoAQH4AQKIAgGoAgO4ArLCnaAGwAIB0gIkZjk0MzE1NzYtNjJiYS00OTcyLTgwMWEtOGU1NTgyOGQ1OWE52AIF4AIB&aid=304142&ucfs=1&arphpl=1&checkin=2023-06-03&checkout=2023-06-12&dest_id=-94604&dest_type=city&group_adults=2&req_adults=2&no_rooms=1&group_children=0&req_children=0&hpos=22&hapos=22&sr_order=popularity&nflt=distance%3D1000%3Boos%3D1%3Breview_score%3D80&srpvid=48956c0ec3e60246&srepoch=1678288927&all_sr_blocks=827230101_347223188_2_0_0&highlighted_blocks=827230101_347223188_2_0_0&matching_block_id=827230101_347223188_2_0_0&sr_pri_blocks=827230101_347223188_2_0_0__199400&from=searchresults#hotelTmpl",
    "title": "Happy House Bregovita by Irundo",
    "price": "US$2.111"
  },
  "Apartments Villa Markiz": {
    "url": "https://www.booking.com/hotel/hr/villa-markiz.de.html?label=gen173nr-1FCAEoggI46AdIB1gEaDuIAQGYAQe4AQfIAQzYAQHoAQH4AQKIAgGoAgO4ArLCnaAGwAIB0gIkZjk0MzE1NzYtNjJiYS00OTcyLTgwMWEtOGU1NTgyOGQ1OWE52AIF4AIB&aid=304142&ucfs=1&arphpl=1&checkin=2023-06-03&checkout=2023-06-12&dest_id=-94604&dest_type=city&group_adults=2&req_adults=2&no_rooms=1&group_children=0&req_children=0&hpos=23&hapos=23&sr_order=popularity&nflt=distance%3D1000%3Boos%3D1%3Breview_score%3D80&srpvid=48956c0ec3e60246&srepoch=1678288927&all_sr_blocks=29317603_351628459_0_0_0&highlighted_blocks=29317603_351628459_0_0_0&matching_block_id=29317603_351628459_0_0_0&sr_pri_blocks=29317603_351628459_0_0_0__141000&from=searchresults#hotelTmpl",
    "title": "Apartments Villa Markiz",
    "price": "US$1.493"
  },
  "Rovinj City Studio": {
    "url": "https://www.booking.com/hotel/hr/rovinj-city-studio.de.html?label=gen173nr-1FCAEoggI46AdIB1gEaDuIAQGYAQe4AQfIAQzYAQHoAQH4AQKIAgGoAgO4ArLCnaAGwAIB0gIkZjk0MzE1NzYtNjJiYS00OTcyLTgwMWEtOGU1NTgyOGQ1OWE52AIF4AIB&aid=304142&ucfs=1&arphpl=1&checkin=2023-06-03&checkout=2023-06-12&dest_id=-94604&dest_type=city&group_adults=2&req_adults=2&no_rooms=1&group_children=0&req_children=0&hpos=24&hapos=24&sr_order=popularity&nflt=distance%3D1000%3Boos%3D1%3Breview_score%3D80&srpvid=48956c0ec3e60246&srepoch=1678288927&all_sr_blocks=825408203_364974136_2_0_0&highlighted_blocks=825408203_364974136_2_0_0&matching_block_id=825408203_364974136_2_0_0&sr_pri_blocks=825408203_364974136_2_0_0__107141&from=searchresults#hotelTmpl",
    "title": "Rovinj City Studio",
    "price": "US$1.134"
  },
  "Deluxe Apartment Vera": {
    "url": "https://www.booking.com/hotel/hr/delux-apartment-vera.de.html?label=gen173nr-1FCAEoggI46AdIB1gEaDuIAQGYAQe4AQfIAQzYAQHoAQH4AQKIAgGoAgO4ArLCnaAGwAIB0gIkZjk0MzE1NzYtNjJiYS00OTcyLTgwMWEtOGU1NTgyOGQ1OWE52AIF4AIB&aid=304142&ucfs=1&arphpl=1&checkin=2023-06-03&checkout=2023-06-12&dest_id=-94604&dest_type=city&group_adults=2&req_adults=2&no_rooms=1&group_children=0&req_children=0&hpos=25&hapos=25&sr_order=popularity&nflt=distance%3D1000%3Boos%3D1%3Breview_score%3D80&srpvid=48956c0ec3e60246&srepoch=1678288927&all_sr_blocks=391285501_269080355_0_0_0&highlighted_blocks=391285501_269080355_0_0_0&matching_block_id=391285501_269080355_0_0_0&sr_pri_blocks=391285501_269080355_0_0_0__177800&from=searchresults#hotelTmpl",
    "title": "Deluxe Apartment Vera",
    "price": "US$1.882"
  },
  "Apartments CASA ROCCIA BIANCA": {
    "url": "https://www.booking.com/hotel/hr/apartment-blue-notte.de.html?label=gen173nr-1FCAEoggI46AdIB1gEaDuIAQGYAQe4AQfIAQzYAQHoAQH4AQKIAgGoAgO4ArLCnaAGwAIB0gIkZjk0MzE1NzYtNjJiYS00OTcyLTgwMWEtOGU1NTgyOGQ1OWE52AIF4AIB&aid=304142&ucfs=1&arphpl=1&checkin=2023-06-03&checkout=2023-06-12&dest_id=-94604&dest_type=city&group_adults=2&req_adults=2&no_rooms=1&group_children=0&req_children=0&hpos=26&hapos=26&sr_order=popularity&nflt=distance%3D1000%3Boos%3D1%3Breview_score%3D80&srpvid=48956c0ec3e60246&srepoch=1678288927&all_sr_blocks=378351603_253245034_2_0_0&highlighted_blocks=378351603_253245034_2_0_0&matching_block_id=378351603_253245034_2_0_0&sr_pri_blocks=378351603_253245034_2_0_0__137894&from=searchresults#hotelTmpl",
    "title": "Apartments CASA ROCCIA BIANCA",
    "price": "US$1.460"
  },
  "Luxury Villa Orh Rovinj": {
    "url": "https://www.booking.com/hotel/hr/villa-orh-rovinj.de.html?label=gen173nr-1FCAEoggI46AdIB1gEaDuIAQGYAQe4AQfIAQzYAQHoAQH4AQKIAgGoAgO4ArLCnaAGwAIB0gIkZjk0MzE1NzYtNjJiYS00OTcyLTgwMWEtOGU1NTgyOGQ1OWE52AIF4AIB&aid=304142&ucfs=1&arphpl=1&checkin=2023-06-03&checkout=2023-06-12&dest_id=-94604&dest_type=city&group_adults=2&req_adults=2&no_rooms=1&group_children=0&req_children=0&hpos=27&hapos=27&sr_order=popularity&nflt=distance%3D1000%3Boos%3D1%3Breview_score%3D80&srpvid=48956c0ec3e60246&srepoch=1678288927&all_sr_blocks=743259001_348984291_0_1_0&highlighted_blocks=743259001_348984291_0_1_0&matching_block_id=743259001_348984291_0_1_0&sr_pri_blocks=743259001_348984291_0_1_0__225000&from_sustainable_property_sr=1&from=searchresults#hotelTmpl",
    "title": "Luxury Villa Orh Rovinj",
    "price": "US$2.382"
  },
  "Studio Apartment La Maison de Catherine": {
    "url": "https://www.booking.com/hotel/hr/lidia-apartments.de.html?label=gen173nr-1FCAEoggI46AdIB1gEaDuIAQGYAQe4AQfIAQzYAQHoAQH4AQKIAgGoAgO4ArLCnaAGwAIB0gIkZjk0MzE1NzYtNjJiYS00OTcyLTgwMWEtOGU1NTgyOGQ1OWE52AIF4AIB&aid=304142&ucfs=1&arphpl=1&checkin=2023-06-03&checkout=2023-06-12&dest_id=-94604&dest_type=city&group_adults=2&req_adults=2&no_rooms=1&group_children=0&req_children=0&hpos=28&hapos=28&sr_order=popularity&nflt=distance%3D1000%3Boos%3D1%3Breview_score%3D80&srpvid=48956c0ec3e60246&srepoch=1678288927&all_sr_blocks=361297904_138915059_4_0_0&highlighted_blocks=361297904_138915059_4_0_0&matching_block_id=361297904_138915059_4_0_0&sr_pri_blocks=361297904_138915059_4_0_0__144000&from=searchresults#hotelTmpl",
    "title": "Studio Apartment La Maison de Catherine",
    "price": "US$1.524"
  },
  "Apartman Delfin": {
    "url": "https://www.booking.com/hotel/hr/apartment-vesna-rovinj1.de.html?label=gen173nr-1FCAEoggI46AdIB1gEaDuIAQGYAQe4AQfIAQzYAQHoAQH4AQKIAgGoAgO4ArLCnaAGwAIB0gIkZjk0MzE1NzYtNjJiYS00OTcyLTgwMWEtOGU1NTgyOGQ1OWE52AIF4AIB&aid=304142&ucfs=1&arphpl=1&checkin=2023-06-03&checkout=2023-06-12&dest_id=-94604&dest_type=city&group_adults=2&req_adults=2&no_rooms=1&group_children=0&req_children=0&hpos=29&hapos=29&sr_order=popularity&nflt=distance%3D1000%3Boos%3D1%3Breview_score%3D80&srpvid=48956c0ec3e60246&srepoch=1678288927&all_sr_blocks=239994201_121112227_0_0_0&highlighted_blocks=239994201_121112227_0_0_0&matching_block_id=239994201_121112227_0_0_0&sr_pri_blocks=239994201_121112227_0_0_0__135000&from=searchresults#hotelTmpl",
    "title": "Apartman Delfin",
    "price": "US$1.429"
  },
  "VILLA ANDREJA - Deluxe Apartments": {
    "url": "https://www.booking.com/hotel/hr/villa-andreja-deluxe-sunlight-apartment.de.html?label=gen173nr-1FCAEoggI46AdIB1gEaDuIAQGYAQe4AQfIAQzYAQHoAQH4AQKIAgGoAgO4ArLCnaAGwAIB0gIkZjk0MzE1NzYtNjJiYS00OTcyLTgwMWEtOGU1NTgyOGQ1OWE52AIF4AIB&aid=304142&ucfs=1&arphpl=1&checkin=2023-06-03&checkout=2023-06-12&dest_id=-94604&dest_type=city&group_adults=2&req_adults=2&no_rooms=1&group_children=0&req_children=0&hpos=30&hapos=30&sr_order=popularity&nflt=distance%3D1000%3Boos%3D1%3Breview_score%3D80&srpvid=48956c0ec3e60246&srepoch=1678288927&all_sr_blocks=752099703_356250724_0_0_0&highlighted_blocks=752099703_356250724_0_0_0&matching_block_id=752099703_356250724_0_0_0&sr_pri_blocks=752099703_356250724_0_0_0__153000&from=searchresults#hotelTmpl",
    "title": "VILLA ANDREJA - Deluxe Apartments",
    "price": "US$1.620"
  },
  "ZITA - Heart of Rovinj, apartment for 2, free parking, 2min center, 5min beach walk": {
    "url": "https://www.booking.com/hotel/hr/hart-of-rovinj-apartment-for-2-free-parking-2min-center-5min-beach-walk.de.html?label=gen173nr-1FCAEoggI46AdIB1gEaDuIAQGYAQe4AQfIAQzYAQHoAQH4AQKIAgGoAgO4ArLCnaAGwAIB0gIkZjk0MzE1NzYtNjJiYS00OTcyLTgwMWEtOGU1NTgyOGQ1OWE52AIF4AIB&aid=304142&ucfs=1&arphpl=1&checkin=2023-06-03&checkout=2023-06-12&dest_id=-94604&dest_type=city&group_adults=2&req_adults=2&no_rooms=1&group_children=0&req_children=0&hpos=31&hapos=31&sr_order=popularity&nflt=distance%3D1000%3Boos%3D1%3Breview_score%3D80&srpvid=48956c0ec3e60246&srepoch=1678288927&all_sr_blocks=875565501_356443909_2_0_0&highlighted_blocks=875565501_356443909_2_0_0&matching_block_id=875565501_356443909_2_0_0&sr_pri_blocks=875565501_356443909_2_0_0__154800&from=searchresults#hotelTmpl",
    "title": "ZITA - Heart of Rovinj, apartment for 2, free parking, 2min center, 5min beach walk",
    "price": "US$1.639"
  },
  "The Attic Rovinj": {
    "url": "https://www.booking.com/hotel/hr/the-attic-rovinj.de.html?label=gen173nr-1FCAEoggI46AdIB1gEaDuIAQGYAQe4AQfIAQzYAQHoAQH4AQKIAgGoAgO4ArLCnaAGwAIB0gIkZjk0MzE1NzYtNjJiYS00OTcyLTgwMWEtOGU1NTgyOGQ1OWE52AIF4AIB&aid=304142&ucfs=1&arphpl=1&checkin=2023-06-03&checkout=2023-06-12&dest_id=-94604&dest_type=city&group_adults=2&req_adults=2&no_rooms=1&group_children=0&req_children=0&hpos=32&hapos=32&sr_order=popularity&nflt=distance%3D1000%3Boos%3D1%3Breview_score%3D80&srpvid=48956c0ec3e60246&srepoch=1678288927&all_sr_blocks=518418901_180680833_2_0_0&highlighted_blocks=518418901_180680833_2_0_0&matching_block_id=518418901_180680833_2_0_0&sr_pri_blocks=518418901_180680833_2_0_0__218025&from=searchresults#hotelTmpl",
    "title": "The Attic Rovinj",
    "price": "US$2.308"
  },
  "Modern and cozy apartments Salt & Pepper in heart of Rovinj": {
    "url": "https://www.booking.com/hotel/hr/modern-and-cozy-apartments-salt-amp-pepper-in-heart-of-rovinj.de.html?label=gen173nr-1FCAEoggI46AdIB1gEaDuIAQGYAQe4AQfIAQzYAQHoAQH4AQKIAgGoAgO4ArLCnaAGwAIB0gIkZjk0MzE1NzYtNjJiYS00OTcyLTgwMWEtOGU1NTgyOGQ1OWE52AIF4AIB&aid=304142&ucfs=1&arphpl=1&checkin=2023-06-03&checkout=2023-06-12&dest_id=-94604&dest_type=city&group_adults=2&req_adults=2&no_rooms=1&group_children=0&req_children=0&hpos=33&hapos=33&sr_order=popularity&nflt=distance%3D1000%3Boos%3D1%3Breview_score%3D80&srpvid=48956c0ec3e60246&srepoch=1678288927&all_sr_blocks=863221001_354680195_4_0_0&highlighted_blocks=863221001_354680195_4_0_0&matching_block_id=863221001_354680195_4_0_0&sr_pri_blocks=863221001_354680195_4_0_0__205000&from=searchresults#hotelTmpl",
    "title": "Modern and cozy apartments Salt & Pepper in heart of Rovinj",
    "price": "US$2.170"
  },
  "Stelle D'oro": {
    "url": "https://www.booking.com/hotel/hr/stelle-d-39-oro.de.html?label=gen173nr-1FCAEoggI46AdIB1gEaDuIAQGYAQe4AQfIAQzYAQHoAQH4AQKIAgGoAgO4ArLCnaAGwAIB0gIkZjk0MzE1NzYtNjJiYS00OTcyLTgwMWEtOGU1NTgyOGQ1OWE52AIF4AIB&aid=304142&ucfs=1&arphpl=1&checkin=2023-06-03&checkout=2023-06-12&dest_id=-94604&dest_type=city&group_adults=2&req_adults=2&no_rooms=1&group_children=0&req_children=0&hpos=9&hapos=9&sr_order=popularity&nflt=distance%3D1000%3Boos%3D1%3Breview_score%3D80&srpvid=0f3d9f44a2b200a3&srepoch=1678315146&all_sr_blocks=647894501_354180880_2_0_0&highlighted_blocks=647894501_354180880_2_0_0&matching_block_id=647894501_354180880_2_0_0&sr_pri_blocks=647894501_354180880_2_0_0__129000&from=searchresults#hotelTmpl",
    "title": "Stelle D'oro",
    "price": "US$1.366"
  },
  "Pisinium Studios": {
    "url": "https://www.booking.com/hotel/hr/apartments-maja-rovinj.de.html?label=gen173nr-1FCAEoggI46AdIB1gEaDuIAQGYAQe4AQfIAQzYAQHoAQH4AQKIAgGoAgO4ArLCnaAGwAIB0gIkZjk0MzE1NzYtNjJiYS00OTcyLTgwMWEtOGU1NTgyOGQ1OWE52AIF4AIB&aid=304142&ucfs=1&arphpl=1&checkin=2023-06-03&checkout=2023-06-12&dest_id=-94604&dest_type=city&group_adults=2&req_adults=2&no_rooms=1&group_children=0&req_children=0&hpos=6&hapos=6&sr_order=popularity&nflt=distance%3D1000%3Boos%3D1%3Breview_score%3D80&srpvid=b3d451bf1a0401b0&srepoch=1678361855&all_sr_blocks=373007401_369669620_0_0_0&highlighted_blocks=373007401_369669620_0_0_0&matching_block_id=373007401_369669620_0_0_0&sr_pri_blocks=373007401_369669620_0_0_0__83867&from=searchresults#hotelTmpl",
    "title": "Pisinium Studios",
    "price": "US$885"
  },
  "Apartments Nevija": {
    "url": "https://www.booking.com/hotel/hr/apartments-nevija.de.html?label=gen173nr-1FCAEoggI46AdIB1gEaDuIAQGYAQe4AQfIAQzYAQHoAQH4AQKIAgGoAgO4ArLCnaAGwAIB0gIkZjk0MzE1NzYtNjJiYS00OTcyLTgwMWEtOGU1NTgyOGQ1OWE52AIF4AIB&aid=304142&ucfs=1&arphpl=1&checkin=2023-06-03&checkout=2023-06-12&dest_id=-94604&dest_type=city&group_adults=2&req_adults=2&no_rooms=1&group_children=0&req_children=0&hpos=17&hapos=17&sr_order=popularity&nflt=distance%3D1000%3Boos%3D1%3Breview_score%3D80&srpvid=22b26705d3e601a4&srepoch=1678372748&all_sr_blocks=179780202_118755901_2_0_0&highlighted_blocks=179780202_118755901_2_0_0&matching_block_id=179780202_118755901_2_0_0&sr_pri_blocks=179780202_118755901_2_0_0__116100&from=searchresults#hotelTmpl",
    "title": "Apartments Nevija",
    "price": "US$1.225"
  },
  "Studio Apartment Kris": {
    "url": "https://www.booking.com/hotel/hr/studio-kris.de.html?label=gen173nr-1FCAEoggI46AdIB1gEaDuIAQGYAQe4AQfIAQzYAQHoAQH4AQKIAgGoAgO4ArLCnaAGwAIB0gIkZjk0MzE1NzYtNjJiYS00OTcyLTgwMWEtOGU1NTgyOGQ1OWE52AIF4AIB&aid=304142&ucfs=1&arphpl=1&checkin=2023-06-03&checkout=2023-06-12&dest_id=-94604&dest_type=city&group_adults=2&req_adults=2&no_rooms=1&group_children=0&req_children=0&hpos=12&hapos=12&sr_order=popularity&nflt=distance%3D1000%3Boos%3D1%3Breview_score%3D80&srpvid=c5825b6f9e0b0842&srepoch=1678453215&all_sr_blocks=251864101_344798269_0_0_0&highlighted_blocks=251864101_344798269_0_0_0&matching_block_id=251864101_344798269_0_0_0&sr_pri_blocks=251864101_344798269_0_0_0__131200&from=searchresults#hotelTmpl",
    "title": "Studio Apartment Kris",
    "price": "US$1.387"
  },
  "Apartments and Rooms Luan": {
    "url": "https://www.booking.com/hotel/hr/apartments-and-rooms-luan.de.html?label=gen173nr-1FCAEoggI46AdIB1gEaDuIAQGYAQe4AQfIAQzYAQHoAQH4AQKIAgGoAgO4ArLCnaAGwAIB0gIkZjk0MzE1NzYtNjJiYS00OTcyLTgwMWEtOGU1NTgyOGQ1OWE52AIF4AIB&aid=304142&ucfs=1&arphpl=1&checkin=2023-06-03&checkout=2023-06-12&dest_id=-94604&dest_type=city&group_adults=2&req_adults=2&no_rooms=1&group_children=0&req_children=0&hpos=13&hapos=13&sr_order=popularity&nflt=distance%3D1000%3Boos%3D1%3Breview_score%3D80&srpvid=c5825b6f9e0b0842&srepoch=1678453215&all_sr_blocks=758379401_344795893_2_0_0&highlighted_blocks=758379401_344795893_2_0_0&matching_block_id=758379401_344795893_2_0_0&sr_pri_blocks=758379401_344795893_2_0_0__143300&from=searchresults#hotelTmpl",
    "title": "Apartments and Rooms Luan",
    "price": "US$1.515"
  },
  "Rovigno Bella sea view Apartment": {
    "url": "https://www.booking.com/hotel/hr/rovigno-bella-apartment.de.html?label=gen173nr-1FCAEoggI46AdIB1gEaDuIAQGYAQe4AQfIAQzYAQHoAQH4AQKIAgGoAgO4ArLCnaAGwAIB0gIkZjk0MzE1NzYtNjJiYS00OTcyLTgwMWEtOGU1NTgyOGQ1OWE52AIF4AIB&aid=304142&ucfs=1&arphpl=1&checkin=2023-06-03&checkout=2023-06-12&dest_id=-94604&dest_type=city&group_adults=2&req_adults=2&no_rooms=1&group_children=0&req_children=0&hpos=24&hapos=24&sr_order=popularity&nflt=distance%3D1000%3Boos%3D1%3Breview_score%3D80&srpvid=c5825b6f9e0b0842&srepoch=1678453215&all_sr_blocks=238691801_344798336_2_0_0&highlighted_blocks=238691801_344798336_2_0_0&matching_block_id=238691801_344798336_2_0_0&sr_pri_blocks=238691801_344798336_2_0_0__239000&from=searchresults#hotelTmpl",
    "title": "Rovigno Bella sea view Apartment",
    "price": "US$2.526"
  },
  "Garzoto rooms and studios": {
    "url": "https://www.booking.com/hotel/hr/studio-baby.de.html?label=gen173nr-1FCAEoggI46AdIB1gEaDuIAQGYAQe4AQfIAQzYAQHoAQH4AQKIAgGoAgO4ArLCnaAGwAIB0gIkZjk0MzE1NzYtNjJiYS00OTcyLTgwMWEtOGU1NTgyOGQ1OWE52AIF4AIB&aid=304142&ucfs=1&arphpl=1&checkin=2023-06-03&checkout=2023-06-12&dest_id=-94604&dest_type=city&group_adults=2&req_adults=2&no_rooms=1&group_children=0&req_children=0&hpos=31&hapos=31&sr_order=popularity&nflt=distance%3D1000%3Boos%3D1%3Breview_score%3D80&srpvid=fc606e04c1260025&srepoch=1678462731&all_sr_blocks=331340602_344798244_2_0_0&highlighted_blocks=331340602_344798244_2_0_0&matching_block_id=331340602_344798244_2_0_0&sr_pri_blocks=331340602_344798244_2_0_0__135400&from=searchresults#hotelTmpl",
    "title": "Garzoto rooms and studios",
    "price": "US$1.431"
  },
  "Studio S. Benedetto": {
    "url": "https://www.booking.com/hotel/hr/studio-s-benedetto.de.html?label=gen173nr-1FCAEoggI46AdIB1gEaDuIAQGYAQe4AQfIAQzYAQHoAQH4AQKIAgGoAgO4ArLCnaAGwAIB0gIkZjk0MzE1NzYtNjJiYS00OTcyLTgwMWEtOGU1NTgyOGQ1OWE52AIF4AIB&aid=304142&ucfs=1&arphpl=1&checkin=2023-06-03&checkout=2023-06-12&dest_id=-94604&dest_type=city&group_adults=2&req_adults=2&no_rooms=1&group_children=0&req_children=0&hpos=35&hapos=35&sr_order=popularity&nflt=distance%3D1000%3Boos%3D1%3Breview_score%3D80&srpvid=fc606e04c1260025&srepoch=1678462731&all_sr_blocks=592984901_346697103_0_0_0&highlighted_blocks=592984901_346697103_0_0_0&matching_block_id=592984901_346697103_0_0_0&sr_pri_blocks=592984901_346697103_0_0_0__124000&from=searchresults#hotelTmpl",
    "title": "Studio S. Benedetto",
    "price": "US$1.311"
  },
  "Dolce Studio Apartmani": {
    "url": "https://www.booking.com/hotel/hr/studio-rovinj-rovinj.de.html?label=gen173nr-1FCAEoggI46AdIB1gEaDuIAQGYAQe4AQfIAQzYAQHoAQH4AQKIAgGoAgO4ArLCnaAGwAIB0gIkZjk0MzE1NzYtNjJiYS00OTcyLTgwMWEtOGU1NTgyOGQ1OWE52AIF4AIB&aid=304142&ucfs=1&arphpl=1&checkin=2023-06-03&checkout=2023-06-12&dest_id=-94604&dest_type=city&group_adults=2&req_adults=2&no_rooms=1&group_children=0&req_children=0&hpos=34&hapos=34&sr_order=popularity&nflt=distance%3D1000%3Boos%3D1%3Breview_score%3D80&srpvid=82ac7616ed4401f7&srepoch=1678466861&all_sr_blocks=649500302_350406533_2_0_0&highlighted_blocks=649500302_350406533_2_0_0&matching_block_id=649500302_350406533_2_0_0&sr_pri_blocks=649500302_350406533_2_0_0__140900&from=searchresults#hotelTmpl",
    "title": "Dolce Studio Apartmani",
    "price": "US$1.489"
  },
  "Luna Rooms and Studios": {
    "url": "https://www.booking.com/hotel/hr/luna-rooms-and-studios.de.html?label=gen173nr-1FCAEoggI46AdIB1gEaDuIAQGYAQe4AQfIAQzYAQHoAQH4AQKIAgGoAgO4ArLCnaAGwAIB0gIkZjk0MzE1NzYtNjJiYS00OTcyLTgwMWEtOGU1NTgyOGQ1OWE52AIF4AIB&aid=304142&ucfs=1&arphpl=1&checkin=2023-06-03&checkout=2023-06-12&dest_id=-94604&dest_type=city&group_adults=2&req_adults=2&no_rooms=1&group_children=0&req_children=0&hpos=15&hapos=15&sr_order=popularity&nflt=distance%3D1000%3Boos%3D1%3Breview_score%3D80&srpvid=16807beee5480617&srepoch=1678469853&all_sr_blocks=374656301_344797966_0_0_0&highlighted_blocks=374656301_344797966_0_0_0&matching_block_id=374656301_344797966_0_0_0&sr_pri_blocks=374656301_344797966_0_0_0__136300&from=searchresults#hotelTmpl",
    "title": "Luna Rooms and Studios",
    "price": "US$1.441"
  }
}